gpu_pairwise/boolean.py
gpu_pairwise-0.0.3.dist-info/LICENSE
gpu_pairwise-0.0.3.dist-info/METADATA
gpu_pairwise-0.0.3.dist-info/WHEEL
gpu_pairwise-0.0.3.dist-info/top_level.txt
gpu_pairwise-0.0.3.dist-info/RECORD
