Metadata-Version: 2.1
Name: gpu-pairwise
Version: 0.0.3
Summary: GPU implementation of various pairwise distance functions
Home-page: https://github.com/stestagg/gpu-pairwise-jaccard
Author: Steve Stagg
Author-email: stestagg@gmail.com
License: UNKNOWN
Project-URL: Bug Tracker, https://github.com/stestagg/gpu-pairwise-jaccard/issues
Platform: UNKNOWN
Classifier: Programming Language :: Python :: 3
Classifier: License :: OSI Approved :: MIT License
Classifier: Operating System :: OS Independent
Requires-Python: >=3.6
Requires-Dist: numba
Requires-Dist: numpy
